{
  "slug": "patria-investimentos",
  "nome": "Patria Investimentos",
  "nota": 6.6,
  "notaLabel": "BOM",
  "avaliacao": "bom",
  "totalFundos": 8,
  "segmentos": [
    "Logistica",
    "Tijolo - Renda Urbana",
    "Crédito (CRI)",
    "Tijolo - Lajes Corporativas",
    "Tijolo - Lajes Corporativas (em liquidação)",
    "Papel - CRI (Gestão Ativa)",
    "Fundo de Fundos"
  ],
  "resumo": "Gestora com 8 fundos analisados: HGLG11, HGRU11, HGCR11, HGRE11, HGPO11, BARI11, CBOP11, HGFF11. Nota média 6.6/10 (BOM).",
  "seo": {
    "title": "Patria Investimentos - Análise da Gestora | Rico aos Poucos",
    "description": "Análise da gestora Patria Investimentos. 8 fundos geridos com nota média 6.6/10. Veja os FIIs: HGLG11, HGRU11, HGCR11, HGRE11, HGPO11, BARI11, CBOP11, HGFF11.",
    "ogTitle": "Patria Investimentos - Análise da Gestora de FIIs",
    "ogDescription": "Patria Investimentos: 8 fundos, nota média 6.6/10. Fundos: HGLG11, HGRU11, HGCR11, HGRE11, HGPO11, BARI11, CBOP11, HGFF11.",
    "twitterTitle": "Patria Investimentos - Gestora de FIIs | Rico aos Poucos",
    "twitterDescription": "Análise da Patria Investimentos: 8 fundos, nota 6.6/10."
  },
  "fundos": [
    {
      "ticker": "HGLG11",
      "nome": "Patria Log FII",
      "segmento": "Logistica",
      "nota": 8,
      "notaLabel": "EXCELENTE",
      "dividendYield": 8.2,
      "pvp": 0.97,
      "sentimento": "otimista"
    },
    {
      "ticker": "HGRU11",
      "nome": "Patria Renda Urbana FII",
      "segmento": "Tijolo - Renda Urbana",
      "nota": 8,
      "notaLabel": "EXCELENTE",
      "dividendYield": 13.8,
      "pvp": 0.97,
      "sentimento": "otimista"
    },
    {
      "ticker": "HGCR11",
      "nome": "Pátria Recebíveis Imobiliários FII",
      "segmento": "Crédito (CRI)",
      "nota": 7.5,
      "notaLabel": "BOM",
      "dividendYield": 12.2,
      "pvp": 1,
      "sentimento": "otimista"
    },
    {
      "ticker": "HGRE11",
      "nome": "Patria Escritórios FII",
      "segmento": "Tijolo - Lajes Corporativas",
      "nota": 7,
      "notaLabel": "BOM",
      "dividendYield": 14.5,
      "pvp": 0.84,
      "sentimento": "otimista"
    },
    {
      "ticker": "HGPO11",
      "nome": "Patria Edifícios Corporativos FII",
      "segmento": "Tijolo - Lajes Corporativas (em liquidação)",
      "nota": 6.5,
      "notaLabel": "BOM",
      "dividendYield": 0,
      "pvp": 0.98,
      "sentimento": "neutro"
    },
    {
      "ticker": "BARI11",
      "nome": "Barigui Recebíveis Imobiliários FII",
      "segmento": "Papel - CRI (Gestão Ativa)",
      "nota": 5.5,
      "notaLabel": "REGULAR",
      "dividendYield": 12.9,
      "pvp": 0.89,
      "sentimento": "neutro"
    },
    {
      "ticker": "CBOP11",
      "nome": "Castello Branco Office Park FII",
      "segmento": "Tijolo - Lajes Corporativas",
      "nota": 5,
      "notaLabel": "REGULAR",
      "dividendYield": 18.1,
      "pvp": 0.46,
      "sentimento": "neutro"
    },
    {
      "ticker": "HGFF11",
      "nome": "Patria Multi FoF FII",
      "segmento": "Fundo de Fundos",
      "nota": 5,
      "notaLabel": "REGULAR",
      "dividendYield": 10.1,
      "pvp": 0.77,
      "sentimento": "neutro"
    }
  ]
}