{
  "meta": {
    "ticker": "GGRC11",
    "nome": "GGR Covepi Renda FII",
    "segmento": "Logístico/Industrial",
    "badges": [
      "Logística + Industrial + Híbrido",
      "99,79% Ocupação",
      "36 Imóveis"
    ],
    "sentimento": "otimista",
    "dataAnalise": "24/02/2026",
    "totalDocumentos": 762
  },
  "seo": {
    "title": "GGRC11 - Análise Completa | GGR Covepi Renda FII",
    "description": "Análise completa do FII GGRC11 baseada em 762 documentos oficiais. Fundo logístico/industrial com 36 imóveis, 99,79% ocupação, DY 12,12%. Portfólio diversificado, guidance R$ 0,10/cota 2026.",
    "keywords": "GGRC11, GGR Covepi, FII logístico, FII industrial, análise GGRC11, dividend yield GGRC11, Zagros Capital, fundo imobiliário logística",
    "ogTitle": "GGRC11 - Análise Completa do FII GGR Covepi Renda 2026",
    "ogDescription": "Análise detalhada do GGRC11: 36 imóveis logísticos e industriais, 99,79% ocupação, DY 12,12%. R$ 2,4 Bi de PL, 257 mil cotistas. Guidance R$ 0,10/cota/mês para 2026.",
    "twitterTitle": "GGRC11 - Análise Completa | FII GGR Covepi Renda",
    "twitterDescription": "Análise do GGRC11: 36 imóveis em 12 estados, 99,79% ocupação, DY 12,12%. 10ª emissão concluída, PL de R$ 2,4 Bi. Projeções 2026."
  },
  "indicadores": {
    "cotacao": 9.9,
    "cotacaoData": "31/12/2025",
    "pvp": 0.88,
    "pvpDesconto": "12% de desconto",
    "dividendYield": 12.12,
    "dividendoMensal": 0.1,
    "dividendoAnual": 1.2,
    "patrimonioLiquido": "R$ 2,4 Bi",
    "vpCota": 11.22,
    "cotistas": 257323,
    "cotistasDetalhe": "214 milhões de cotas",
    "ocupacao": 99.79,
    "wault": 4.94,
    "numImoveis": 36,
    "ablTotal": "711 mil",
    "numEstados": 12,
    "numInquilinos": 35
  },
  "recomendacao": {
    "nota": 8,
    "veredicto": "COMPRA",
    "cor": "emerald",
    "resumo": "O <strong class=\"text-emerald-400\">GGRC11</strong> apresenta fundamentos sólidos: <strong class=\"text-emerald-400\">99,79% de ocupação</strong>, <strong class=\"text-emerald-400\">DY de 12,12% a.a.</strong> com spread de 431 bps sobre NTN-B 5Y, guidance de <strong class=\"text-emerald-400\">R$ 0,10/cota/mês para 2026</strong>, portfólio com <strong class=\"text-blue-400\">36 ativos diversificados</strong> em 12 estados, e P/VP de 0,88 oferecendo <strong class=\"text-emerald-400\">12% de desconto</strong> sobre o valor patrimonial. Crescimento expressivo em 2025: PL +74,1%, cotistas +82,1%, liquidez +219,5%."
  },
  "quickStats": [
    {
      "label": "Patrimônio",
      "valor": "R$ 2,4 Bi",
      "detalhe": "VP/cota: R$ 11,22",
      "detalheHtml": "VP/cota: <span class=\"font-semibold text-blue-400\">R$ 11,22</span>",
      "icone": "building",
      "corIcone": "blue"
    },
    {
      "label": "Rendimento",
      "valor": "R$ 0,10",
      "valorSufixo": "/mês",
      "detalhe": "R$ 1,20/ano | DY 12,12%",
      "icone": "money",
      "corIcone": "emerald",
      "corValor": "emerald"
    },
    {
      "label": "Cotistas",
      "valor": "257.323",
      "detalhe": "214 milhões de cotas",
      "icone": "users",
      "corIcone": "purple"
    },
    {
      "label": "Preço Justo",
      "valor": "R$ 10,50",
      "detalhe": "+6% upside",
      "detalheIcone": "arrowUp",
      "icone": "chart",
      "corIcone": "amber",
      "corValor": "blue"
    }
  ],
  "pontosAtencao": [
    {
      "titulo": "Alavancagem via CRIs",
      "descricao": "O fundo possui R$ 273,9 milhões em obrigações por securitização (CRIs), representando cerca de 11,4% do PL. São 7 CRIs com taxas de IPCA+6,5% a IPCA+9,5% e CDI 100%. Saldo devedor controlado, mas juros altos pressionam resultado em cenário de Selic elevada.",
      "severidade": "amber"
    },
    {
      "titulo": "WAULT curto (4,94 anos)",
      "descricao": "O WAULT de 4,94 anos é relativamente curto para o segmento logístico. Em 2027, vencem contratos relevantes como Renault (11,5% da receita), Ambev Guarulhos/Itajaí e outros, totalizando ~26% da receita. Risco de vacância temporária ou renegociação desfavorável.",
      "severidade": "orange"
    },
    {
      "titulo": "Covolan em Recuperação Judicial",
      "descricao": "A Covolan, locatária de imóvel industrial em Santa Bárbara D'Oeste/SP (4,5% da receita), está em recuperação judicial. Há valores depositados em juízo referentes a aluguéis anteriores. PDD de R$ 2,49 milhões já constituída. Venda dos imóveis Covolan por R$ 94,9 Mi concluída.",
      "severidade": "orange"
    },
    {
      "titulo": "Crescimento acelerado em 2025",
      "descricao": "O GGRC11 cresceu 74,1% em PL e 82,1% em cotistas durante 2025, com conclusão da 10ª emissão. Recorde de 36.617 novos cotistas só em dezembro. O crescimento rápido exige monitoramento da integração de novos ativos e manutenção da qualidade do portfólio.",
      "severidade": "emerald"
    }
  ],
  "gestora": {
    "nome": "Zagros Capital (GGR Gestão de Recursos)",
    "nota": 8,
    "notaLabel": "EXCELENTE",
    "stats": [
      {
        "label": "No mercado",
        "valor": "Desde 2017"
      },
      {
        "label": "Patrimônio",
        "valor": "R$ 2,4 Bi"
      },
      {
        "label": "Emissões",
        "valor": "10",
        "cor": "emerald"
      }
    ],
    "resumo": "Gestão ativa comprovada pela Zagros Capital: <strong class=\"text-emerald-400\">36 ativos em 12 estados</strong>, reciclagem eficiente com TIR de 16,94% na venda do CD Campinas, <strong class=\"text-emerald-400\">crescimento de 74,1% no PL</strong> em 2025, e transparência exemplar com relatórios detalhados e vídeos mensais. Guidance claro de R$ 0,10/cota/mês para 2026.",
    "link": "../../gestores/zagros-capital/"
  },
  "taxas": {
    "subtitulo": "Competitivas para o segmento",
    "glowCor": "green",
    "itens": [
      {
        "label": "Taxa de Administração e Gestão",
        "valor": "1,10% a.a.",
        "detalhe": "Sobre o patrimônio líquido",
        "corBorda": "emerald"
      },
      {
        "label": "Taxa de Performance",
        "valor": "Não há",
        "detalhe": "Sem taxa de performance",
        "corBorda": "emerald"
      },
      {
        "label": "Taxa de Custódia",
        "valor": "0%",
        "detalhe": "Incluída na administração",
        "corBorda": "slate"
      }
    ],
    "comparativoTitulo": "Comparativo com FIIs Logísticos",
    "comparativo": [
      {
        "ticker": "GGRC11",
        "taxa": "1,10%",
        "perf": "Sem performance",
        "destaque": true
      },
      {
        "ticker": "HGLG11",
        "taxa": "0,60%",
        "perf": "+20% perf. s/ IPCA+6%"
      },
      {
        "ticker": "XPLG11",
        "taxa": "0,95%",
        "perf": "+20% perf. s/ IPCA+6%"
      },
      {
        "ticker": "BTLG11",
        "taxa": "0,90%",
        "perf": "+20% perf. s/ IPCA+6%"
      }
    ],
    "detalhes": [
      {
        "label": "Administrador",
        "valor": "Banvox DTVM (ex-CM Capital)"
      },
      {
        "label": "Escriturador",
        "valor": "Banvox DTVM"
      },
      {
        "label": "Custodiante",
        "valor": "Banvox DTVM"
      }
    ]
  },
  "portfolio": {
    "stats": [
      {
        "label": "Imóveis",
        "valor": "36"
      },
      {
        "label": "m2 ABL",
        "valor": "711 mil"
      },
      {
        "label": "Anos WAULT",
        "valor": "4,94",
        "cor": "amber"
      },
      {
        "label": "Ocupação",
        "valor": "99,79%",
        "cor": "emerald"
      }
    ],
    "tipologiaChart": {
      "labels": [
        "Logístico",
        "Industrial",
        "Híbrido"
      ],
      "data": [
        67,
        18,
        15
      ],
      "cores": [
        "#10b981",
        "#3b82f6",
        "#8b5cf6"
      ]
    },
    "locatarioChart": {
      "labels": [
        "Renault",
        "Ambev",
        "Americanas",
        "Triple A",
        "Covolan",
        "Outros"
      ],
      "data": [
        11.5,
        11.1,
        10.8,
        8.7,
        4.5,
        53.4
      ],
      "cores": [
        "#3b82f6",
        "#f59e0b",
        "#ef4444",
        "#8b5cf6",
        "#6b7280",
        "#10b981"
      ]
    },
    "locatariosNota": {
      "titulo": "Portfólio Diversificado (Dezembro 2025)",
      "texto": "O GGRC11 possui <strong class=\"text-white\">35 locatários diferentes</strong> em seu portfólio, demonstrando <strong class=\"text-emerald-400\">alta diversificação</strong>. Os maiores locatários por receita são Renault (11,5%), Ambev (11,1%), Americanas (10,8%) e Triple A (8,7%). Contratos reajustados majoritariamente pelo <strong class=\"text-blue-400\">IPCA (90,28%)</strong>, com IGPM (7,49%) e INPC (2,23%)."
    },
    "locatarios": [
      {
        "nome": "Renault",
        "setor": "Automotivo",
        "receita": "11,5%",
        "rating": "Investment Grade",
        "ratingCor": "emerald",
        "risco": "Venc. 2027",
        "riscoCor": "orange"
      },
      {
        "nome": "Ambev",
        "setor": "Alimentos e Bebidas",
        "receita": "11,1%",
        "rating": "AAA",
        "ratingCor": "emerald",
        "risco": "Baixo",
        "riscoCor": "emerald"
      },
      {
        "nome": "Americanas",
        "setor": "Comércio Varejista",
        "receita": "10,8%",
        "rating": "Em recuperação",
        "ratingCor": "orange",
        "risco": "Moderado",
        "riscoCor": "amber"
      },
      {
        "nome": "Triple A FII",
        "setor": "Logística",
        "receita": "8,7%",
        "rating": "FII",
        "ratingCor": "blue",
        "risco": "Baixo",
        "riscoCor": "emerald"
      },
      {
        "nome": "Aethra + Outros",
        "setor": "Diversos",
        "receita": "57,9%",
        "rating": "Diversos",
        "ratingCor": "blue",
        "risco": "Diversificado",
        "riscoCor": "emerald"
      }
    ],
    "riscoResumo": [
      {
        "label": "Ativos Baixo Risco",
        "valor": 20,
        "cor": "emerald"
      },
      {
        "label": "Ativos Risco Moderado",
        "valor": 8,
        "cor": "blue"
      },
      {
        "label": "Ativos Venc. Próximo",
        "valor": 7,
        "cor": "amber"
      },
      {
        "label": "Ativo Problemático",
        "valor": 1,
        "cor": "orange"
      }
    ],
    "riscoNota": "O portfólio é bastante diversificado com <strong class=\"text-emerald-400\">35 locatários em 36 imóveis</strong>. Os 7 ativos marcados como \"Vencimento Próximo\" têm contratos até 2027-2028 e representam ~26% da receita. A Covolan é marcada como \"Problemático\" por estar em recuperação judicial, mas a venda dos imóveis já foi concluída. Com a venda do CD Campinas, a vacância caiu de 4,08% para <strong class=\"text-emerald-400\">0,21%</strong>."
  },
  "timeline": {
    "subtitulo": "De startup a um dos maiores FIIs logísticos do Brasil",
    "periodos": [
      {
        "periodo": "2017-2018",
        "label": "FUNDAÇÃO",
        "cor": "blue",
        "descricao": "Início das atividades em abril de 2017 com foco em locação atípica (built to suit, retrofit, sale and leaseback).",
        "pontos": [
          "Início em abril/2017 como GGR Covepi Renda FII",
          "Foco em imóveis industriais e logísticos",
          "Estratégia de contratos atípicos de longo prazo",
          "Primeiras aquisições em São Paulo e Paraná"
        ]
      },
      {
        "periodo": "2019-2021",
        "label": "EXPANSÃO INICIAL",
        "cor": "emerald",
        "descricao": "Crescimento orgânico com aquisições seletivas e manutenção de alta ocupação.",
        "pontos": [
          "Portfólio expandido para diversos estados",
          "Diversificação de locatários e setores",
          "Manutenção de dividendos consistentes",
          "Base de cotistas em crescimento constante"
        ]
      },
      {
        "periodo": "2022-2023",
        "label": "CONSOLIDAÇÃO",
        "cor": "purple",
        "descricao": "Amadurecimento da gestão e foco na qualidade dos ativos.",
        "pontos": [
          "Reciclagem de portfólio com vendas estratégicas",
          "Novas emissões para crescimento",
          "Ampliação da presença geográfica",
          "Gestão pela Zagros Capital consolidada"
        ]
      },
      {
        "periodo": "2024",
        "label": "TRANSFORMAÇÃO",
        "cor": "amber",
        "descricao": "9ª emissão e reestruturação da administração.",
        "pontos": [
          "9ª emissão de cotas concluída com sucesso",
          "Mudança de administrador para Banvox DTVM",
          "Aquisição de novos ativos logísticos",
          "Crescimento acelerado da base de cotistas"
        ]
      },
      {
        "periodo": "2025-2026",
        "label": "RECORDE HISTÓRICO",
        "cor": "emerald",
        "descricao": "Ano de recordes absolutos em todos os indicadores. 10ª emissão, desinvestimentos estratégicos e guidance otimista.",
        "pontos": [
          "<strong class=\"text-emerald-400\">10ª emissão de cotas concluída (214 milhões de cotas)</strong>",
          "<strong class=\"text-emerald-400\">PL +74,1%: de R$ 1,38 Bi para R$ 2,4 Bi</strong>",
          "<strong class=\"text-purple-400\">Venda Covolan por R$ 94,9 Mi</strong>",
          "<strong class=\"text-purple-400\">Venda CD Campinas por R$ 77 Mi (TIR 16,94%)</strong>",
          "<strong class=\"text-blue-400\">Aquisição Air Liquide Campinas concluída</strong>",
          "<strong class=\"text-emerald-400\">Renovação Ambev Santa Luzia por +5 anos (até 2030)</strong>",
          "<strong class=\"text-emerald-400\">Vacância reduzida de 4,08% para 0,21%</strong>",
          "Cotistas +82,1%: 141 mil para 257 mil | Liquidez +219,5%"
        ]
      }
    ],
    "resumoTrajetoria": {
      "titulo": "Resumo da trajetória - POSITIVA:",
      "texto": "O GGRC11 evoluiu de um fundo com foco em locação atípica para um dos <strong class=\"text-emerald-400\">maiores FIIs logísticos/industriais do Brasil</strong>, com patrimônio de R$ 2,4 bilhões. Em 2025, o fundo bateu recordes: <strong class=\"text-emerald-400\">PL +74,1%</strong>, <strong class=\"text-emerald-400\">cotistas +82,1%</strong>, <strong class=\"text-emerald-400\">liquidez +219,5%</strong>. A reciclagem de ativos com TIR de 16,94% e a redução da vacância para 0,21% demonstram a <strong class=\"text-emerald-400\">qualidade da gestão ativa</strong> pela Zagros Capital."
    },
    "crescimento": [
      {
        "label": "Crescimento PL 2025",
        "valor": "+74,1%",
        "detalhe": "R$ 1,38 Bi para R$ 2,4 Bi"
      },
      {
        "label": "Crescimento Cotistas",
        "valor": "+82,1%",
        "detalhe": "141 mil para 257 mil"
      },
      {
        "label": "Crescimento ABL",
        "valor": "+22,6%",
        "detalhe": "580 mil para 711 mil m2"
      },
      {
        "label": "Crescimento Liquidez",
        "valor": "+219,5%",
        "detalhe": "Volume negociado anual"
      }
    ]
  },
  "tese": {
    "resumo": "GGRC11 é um <strong class=\"text-emerald-400\">FII logístico/industrial diversificado</strong> com 36 imóveis em 12 estados, ocupação de 99,79% e 35 locatários. A gestora Zagros Capital entrega <strong class=\"text-emerald-400\">dividendos consistentes de R$ 0,10/cota/mês</strong> (DY 12,12%), com guidance mantido para 2026. O P/VP de 0,88 oferece 12% de desconto sobre o VP, e o fundo está entre os <strong class=\"text-emerald-400\">3 maiores crescimentos</strong> do mercado de FIIs em 2025. Principal monitoramento: WAULT curto (4,94 anos) e vencimentos relevantes em 2027.",
    "paraQuem": [
      "Investidores que buscam <strong class=\"text-emerald-400\">renda mensal de R$ 0,10/cota</strong> com DY acima de 12%",
      "Perfil <strong class=\"text-emerald-400\">moderado</strong> que valoriza diversificação de locatários",
      "Quem busca <strong class=\"text-emerald-400\">exposição logística/industrial</strong> com desconto sobre VP",
      "Investidores que apreciam <strong class=\"text-emerald-400\">transparência e gestão ativa</strong>"
    ],
    "naoParaQuem": [
      "Quem busca <strong class=\"text-amber-400\">WAULT muito longo</strong> (>10 anos)",
      "Investidores que rejeitam <strong class=\"text-amber-400\">exposição a locatários em recuperação judicial</strong> (Covolan)",
      "Perfil <strong class=\"text-amber-400\">ultra-conservador</strong> que busca apenas RF pura",
      "Quem prefere <strong class=\"text-amber-400\">fundos sem alavancagem</strong> via CRIs"
    ]
  },
  "dividendos": {
    "chartLabels": [
      "Jul/25",
      "Ago/25",
      "Set/25",
      "Out/25",
      "Nov/25",
      "Dez/25"
    ],
    "chartData": [
      0.1,
      0.1,
      0.1,
      0.1,
      0.1,
      0.1
    ],
    "chartCor": "#10b981",
    "chartYMin": 0.08,
    "chartYMax": 0.12,
    "totaisAnuais": [
      {
        "ano": "2021",
        "valor": "R$ 0,90"
      },
      {
        "ano": "2022",
        "valor": "R$ 0,93"
      },
      {
        "ano": "2023",
        "valor": "R$ 0,98"
      },
      {
        "ano": "2024",
        "valor": "R$ 1,05",
        "cor": "emerald"
      },
      {
        "ano": "2025",
        "valor": "R$ 1,20",
        "cor": "emerald",
        "destaque": true
      }
    ],
    "guidance": {
      "periodo": "2026",
      "faixa": "R$ 0,10",
      "unidade": "por cota/mês (guidance base)"
    },
    "stats": [
      {
        "label": "DY Mensal (Dez/25)",
        "valor": "1,01%"
      },
      {
        "label": "DY Anualizado",
        "valor": "12,12%",
        "cor": "emerald"
      },
      {
        "label": "Spread vs NTN-B 5Y",
        "valor": "+431 bps",
        "cor": "emerald"
      },
      {
        "label": "Spread vs Pares",
        "valor": "+302 bps",
        "cor": "emerald"
      },
      {
        "label": "Tendência",
        "valor": "Estável",
        "cor": "emerald"
      }
    ]
  },
  "ativosDetalhados": {
    "subtitulo": "Análise dos principais ativos e grupos de ativos do portfólio (Dez/2025)",
    "itens": [
      {
        "nome": "CD Renault — Quatro Barras/PR",
        "tipo": "Galpão Logístico — Centro de Distribuição Automotivo",
        "icone": "🚗",
        "corIcone": "blue",
        "corBorda": "blue",
        "participacao": "11,5%",
        "participacaoCor": "blue",
        "descricao": "Centro de Distribuição da Renault do Brasil localizado em Quatro Barras/PR, com <strong class=\"text-blue-400\">66.779 m² de ABL</strong> e 249.000 m² de terreno. O maior ativo individual do portfólio, adquirido em Out/2025 do VTLT11 (Votorantim Logística) por R$ 208 milhões via compensação na 10ª emissão de cotas. Galpão padrão construtivo AA com 12m de pé direito, 68 docas, 110 vagas para caminhões e sprinklers. Localizado a 30 km da fábrica da Renault em São José dos Pinhais e a 5 km da Rodovia Régis Bittencourt. Cap Rate estimado de 13,27% a.a. no 1º ano. Em dezembro/2025 foi iniciada obra de reparo na cobertura (prazo 4 meses).",
        "risco": "Moderado",
        "qualidade": "Excelente",
        "relevancia": "Maior ativo individual",
        "contrato": {
          "tipo": "Atípico BTS",
          "termino": "2027",
          "terminoCor": "amber",
          "reajuste": "IPCA",
          "multa": "Saldo remanescente do aluguel"
        },
        "pontos": [
          {
            "texto": "Maior participação individual na receita (11,5%) — aluguel de ~R$ 2,3 Mi/mês",
            "cor": "blue"
          },
          {
            "texto": "Cap Rate de 13,27% a.a. — aquisição com excelente rendimento implícito",
            "cor": "emerald"
          },
          {
            "texto": "Padrão construtivo AA, 68 docas, 12m pé direito — galpão de primeira linha",
            "cor": "emerald"
          },
          {
            "texto": "Vencimento em 2027 — risco de não renovação do maior contrato do fundo",
            "cor": "red"
          },
          {
            "texto": "Renault é investment grade, mas concentração setorial automotiva é risco",
            "cor": "amber"
          },
          {
            "texto": "Obra de reparo na cobertura em andamento (previsão: 4 meses)",
            "cor": "amber"
          }
        ]
      },
      {
        "nome": "CDs Ambev — 4 unidades (GRU, Itajaí, Pelotas, Santa Luzia)",
        "tipo": "Galpões Logísticos — Centros de Distribuição Alimentos e Bebidas",
        "icone": "🍺",
        "corIcone": "emerald",
        "corBorda": "emerald",
        "participacao": "11,1%",
        "participacaoCor": "emerald",
        "descricao": "Conjunto de 4 Centros de Distribuição da Ambev em diferentes estados: <strong class=\"text-emerald-400\">Guarulhos/SP</strong> (13.484 m², venc. Jul/2027), <strong class=\"text-emerald-400\">Itajaí/SC</strong> (9.433 m², venc. Ago/2027), <strong class=\"text-emerald-400\">Pelotas/RS</strong> (9.913 m², venc. Mar/2030) e <strong class=\"text-emerald-400\">Santa Luzia/MG</strong> (16.120 m², venc. Set/2030). ABL total de 48.950 m². A Ambev é classificada como AAA (rating máximo). Em dez/2025, o contrato de Santa Luzia foi renovado por +5 anos (novo vencimento em 2030), reforçando a estabilidade. Galpões com 10 a 12m de pé direito e capacidade de piso de 5 a 8 ton/m².",
        "risco": "Baixo",
        "qualidade": "Excelente",
        "relevancia": "2º maior locatário (AAA)",
        "contrato": {
          "tipo": "Atípico BTS / Típico (misto)",
          "termino": "Jul/2027 a Set/2030",
          "terminoCor": "blue",
          "reajuste": "IPCA",
          "multa": "Variável por unidade"
        },
        "pontos": [
          {
            "texto": "Ambev é locatário AAA — risco de crédito praticamente inexistente",
            "cor": "emerald"
          },
          {
            "texto": "Renovação de Santa Luzia por +5 anos (até 2030) celebrada em Dez/2025",
            "cor": "emerald"
          },
          {
            "texto": "Diversificação geográfica: 4 estados (SP, SC, RS, MG)",
            "cor": "emerald"
          },
          {
            "texto": "Guarulhos e Itajaí vencem em 2027 — monitorar renovação",
            "cor": "amber"
          },
          {
            "texto": "11,1% da receita em um único locatário — concentração moderada",
            "cor": "blue"
          }
        ]
      },
      {
        "nome": "CD Americanas — Uberlândia/MG",
        "tipo": "Galpão Logístico — Centro de Distribuição Varejo",
        "icone": "📦",
        "corIcone": "purple",
        "corBorda": "purple",
        "participacao": "10,8%",
        "participacaoCor": "purple",
        "descricao": "Centro de Distribuição da Americanas S.A. localizado em Uberlândia/MG, com <strong class=\"text-purple-400\">89.188 m² de ABL</strong> — o maior galpão individual do portfólio em área. Galpão logístico com 10,5m de pé direito (variando de 9,5 a 11,85m) e capacidade de piso de 6 ton/m². A Americanas está em recuperação judicial desde Jan/2023, mas mantém os pagamentos de aluguel em dia para este ativo. O fundo possui CRI Americanas no valor de R$ 53,4 Mi (IPCA+7,5% a.a.) vinculado à operação, o que adiciona uma camada de segurança.",
        "risco": "Elevado",
        "qualidade": "Boa",
        "relevancia": "3º maior locatário (risco elevado)",
        "contrato": {
          "tipo": "Atípico BTS",
          "termino": "Set/2027",
          "terminoCor": "amber",
          "reajuste": "IPCA",
          "multa": "Saldo remanescente do aluguel"
        },
        "pontos": [
          {
            "texto": "Maior galpão do portfólio: 89.188 m² de ABL — ativo estratégico em Uberlândia",
            "cor": "blue"
          },
          {
            "texto": "Americanas em recuperação judicial — risco de crédito elevado",
            "cor": "red"
          },
          {
            "texto": "Aluguéis sendo pagos normalmente — operação estável no imóvel",
            "cor": "emerald"
          },
          {
            "texto": "CRI Americanas de R$ 53,4 Mi (IPCA+7,5%) oferece proteção adicional",
            "cor": "blue"
          },
          {
            "texto": "Vencimento em Set/2027 — concentra risco de vacância futura",
            "cor": "amber"
          },
          {
            "texto": "Localização premium em Uberlândia (hub logístico do Triângulo Mineiro)",
            "cor": "emerald"
          }
        ]
      },
      {
        "nome": "Triple A FII — Ativos Indiretos (Cotia/SP e Rio de Janeiro/RJ)",
        "tipo": "FOF — Cotas de FII Logístico (Via Varejo + CD Cotia)",
        "icone": "📊",
        "corIcone": "purple",
        "corBorda": "purple",
        "participacao": "8,7%",
        "participacaoCor": "purple",
        "descricao": "Posição no Triple A FII que confere exposição indireta a dois grandes galpões logísticos: <strong class=\"text-purple-400\">Via Varejo em Duque de Caxias/RJ</strong> (145.578 m² de ABL, pé direito 12,5m) e <strong class=\"text-purple-400\">CD Cotia/SP</strong> (76.878 m² de ABL, pé direito 12,0m). ABL indireta total de 222.456 m². Em Set/2025, o GGRC11 adquiriu do BLMG11 a totalidade das cotas detidas no Triple A (1.125.000 ordinárias + 500.000 preferenciais classe B), duplicando sua posição anterior. O valor da operação foi de R$ 125 milhões (incluindo terreno Cabreúva), via compensação na 10ª emissão. Receita mensal adicional estimada de R$ 870.000. O GGRC11 também possui CRI Triple A de R$ 48,9 Mi (100% CDI).",
        "risco": "Moderado",
        "qualidade": "Boa",
        "relevancia": "4º maior fonte de receita",
        "contrato": {
          "tipo": "Cotas de FII (sem vencimento)",
          "reajuste": "Variação de mercado + dividendos",
          "multa": "N/A — liquidez de mercado"
        },
        "pontos": [
          {
            "texto": "ABL indireta de 222.456 m² — maior exposição em área do portfólio via FII",
            "cor": "blue"
          },
          {
            "texto": "Posição dobrada após aquisição do BLMG11 em Set/2025 (R$ 125 Mi)",
            "cor": "emerald"
          },
          {
            "texto": "CRI Triple A de R$ 48,9 Mi (100% CDI) complementa receita da posição",
            "cor": "blue"
          },
          {
            "texto": "Dupla camada de gestão: taxa do GGRC11 + taxa do Triple A",
            "cor": "amber"
          },
          {
            "texto": "Risco de governança: dependência da gestão do Triple A para os ativos indiretos",
            "cor": "amber"
          }
        ]
      },
      {
        "nome": "Complexo Covolan — Santa Bárbara D'Oeste/SP (em desinvestimento)",
        "tipo": "Imóvel Industrial — Têxtil (venda contratada)",
        "icone": "🏭",
        "corIcone": "amber",
        "corBorda": "amber",
        "participacao": "4,5%",
        "participacaoCor": "amber",
        "descricao": "Complexo industrial em Santa Bárbara D'Oeste/SP, com <strong class=\"text-amber-400\">38.132 m² de ABL</strong>, locado à Covolan Indústria Têxtil, que está em recuperação judicial. Em Dez/2025, o GGRC11 celebrou a venda dos imóveis por R$ 94,9 milhões, a serem pagos em parcelas (3% sinal Jan-Mar/2026, 44% em 58 parcelas mensais de R$ 730 mil a partir de Abr/2026, e 53% em 11 parcelas semestrais). Lucro estimado de R$ 21 milhões (~R$ 0,098/cota). O fundo possui PDD de R$ 2,49 Mi constituída. Valores devidos pela Covolan referentes a aluguéis anteriores à RJ permanecem integralmente devidos conforme plano de recuperação.",
        "risco": "Alto",
        "qualidade": "Regular",
        "relevancia": "Ativo problemático (desinvestimento)",
        "contrato": {
          "tipo": "Atípico (em desinvestimento)",
          "termino": "Abr/2034 (original)",
          "terminoCor": "red",
          "reajuste": "IPCA",
          "multa": "N/A — venda contratada"
        },
        "pontos": [
          {
            "texto": "Venda contratada por R$ 94,9 Mi — lucro estimado de R$ 21 Mi (~R$ 0,098/cota)",
            "cor": "emerald"
          },
          {
            "texto": "Covolan em recuperação judicial — risco de crédito já materializado",
            "cor": "red"
          },
          {
            "texto": "PDD de R$ 2,49 Mi constituída — provisão conservadora",
            "cor": "blue"
          },
          {
            "texto": "Pagamento parcelado até ~2031 — recebíveis de longo prazo com risco de inadimplência",
            "cor": "amber"
          },
          {
            "texto": "Alienação fiduciária em garantia do saldo devedor — mitigação parcial de risco",
            "cor": "blue"
          },
          {
            "texto": "Valores de aluguéis depostos em juízo podem gerar ganho não recorrente no futuro",
            "cor": "emerald"
          }
        ]
      },
      {
        "nome": "Aethra — São José dos Pinhais/PR",
        "tipo": "Imóvel Híbrido — Indústria Automotiva",
        "icone": "⚙️",
        "corIcone": "blue",
        "corBorda": "blue",
        "participacao": "5,1%",
        "participacaoCor": "blue",
        "descricao": "Complexo industrial-logístico da Aethra Sistemas Automotivos em São José dos Pinhais/PR, com <strong class=\"text-blue-400\">22.120 m² de ABL</strong> e pé direito de 7,5m (variando de 7 a 8m). Localizado próximo ao polo automotivo de Curitiba, atende à cadeia de fornecimento da indústria automotiva. A Aethra é fornecedora de estampados e conjuntos soldados para montadoras, com clientes como Renault, Volkswagen e Fiat. Contrato com vencimento em Nov/2030, oferecendo boa previsibilidade de receita.",
        "risco": "Moderado",
        "qualidade": "Boa",
        "relevancia": "5º maior locatário",
        "contrato": {
          "tipo": "Atípico",
          "termino": "Nov/2030",
          "terminoCor": "emerald",
          "reajuste": "IPCA",
          "multa": "Saldo remanescente do aluguel"
        },
        "pontos": [
          {
            "texto": "Contrato longo até Nov/2030 — 5 anos de receita previsível",
            "cor": "emerald"
          },
          {
            "texto": "Polo automotivo de Curitiba — localização estratégica para a cadeia automotiva",
            "cor": "emerald"
          },
          {
            "texto": "Setor automotivo cíclico — vulnerável a desaceleração econômica",
            "cor": "amber"
          },
          {
            "texto": "5,1% da receita — participação relevante mas diversificada",
            "cor": "blue"
          }
        ]
      },
      {
        "nome": "Benteler — Igarassu/PE",
        "tipo": "Imóvel Industrial — Autopeças",
        "icone": "🔧",
        "corIcone": "blue",
        "corBorda": "blue",
        "participacao": "3,6%",
        "participacaoCor": "blue",
        "descricao": "Planta industrial da Benteler Automotive em Igarassu/PE, com <strong class=\"text-blue-400\">15.163 m² de ABL</strong>, 14m de pé direito e capacidade de piso de 5 ton/m². A Benteler é um grupo industrial alemão que fabrica componentes estruturais para a indústria automotiva. A planta de Igarassu atende à fábrica da Fiat/Stellantis em Goiana/PE. Contrato com vencimento em Jun/2030.",
        "risco": "Baixo",
        "qualidade": "Boa",
        "relevancia": "Industrial premium no Nordeste",
        "contrato": {
          "tipo": "Atípico BTS",
          "termino": "Jun/2030",
          "terminoCor": "emerald",
          "reajuste": "IPCA",
          "multa": "Saldo remanescente do aluguel"
        },
        "pontos": [
          {
            "texto": "Benteler: grupo alemão com presença global — risco de crédito baixo",
            "cor": "emerald"
          },
          {
            "texto": "Contrato atípico BTS até Jun/2030 — boa previsibilidade de receita",
            "cor": "emerald"
          },
          {
            "texto": "14m de pé direito — ativo industrial de alto padrão",
            "cor": "blue"
          },
          {
            "texto": "Localizado no Nordeste — menor liquidez para eventual vacância",
            "cor": "amber"
          }
        ]
      },
      {
        "nome": "VW MAN — Resende/RJ",
        "tipo": "Galpão Logístico — Automotivo/Caminhões",
        "icone": "🚛",
        "corIcone": "blue",
        "corBorda": "blue",
        "participacao": "3,7%",
        "participacaoCor": "blue",
        "descricao": "Imóvel logístico da Volkswagen Caminhões e Ônibus (MAN Latin America) em Resende/RJ, com <strong class=\"text-blue-400\">23.867 m² de ABL</strong> e 12m de pé direito. Localizado próximo à fábrica de caminhões da VW/MAN em Resende, um dos maiores complexos industriais do Sul Fluminense. Contrato com vencimento em Jun/2030.",
        "risco": "Baixo",
        "qualidade": "Boa",
        "relevancia": "Locatário premium automotivo",
        "contrato": {
          "tipo": "Atípico",
          "termino": "Jun/2030",
          "terminoCor": "emerald",
          "reajuste": "IPCA",
          "multa": "Saldo remanescente do aluguel"
        },
        "pontos": [
          {
            "texto": "VW/MAN: multinacional com rating investment grade — risco de crédito muito baixo",
            "cor": "emerald"
          },
          {
            "texto": "Proximidade com a fábrica de caminhões em Resende — ativo essencial para operação",
            "cor": "emerald"
          },
          {
            "texto": "Contrato até Jun/2030 — 4+ anos de previsibilidade",
            "cor": "emerald"
          },
          {
            "texto": "Setor de caminhões com perspectiva positiva (logística brasileira em expansão)",
            "cor": "blue"
          }
        ]
      },
      {
        "nome": "Ceratti — Vinhedo/SP",
        "tipo": "Imóvel Híbrido — Indústria Alimentícia",
        "icone": "🥩",
        "corIcone": "emerald",
        "corBorda": "emerald",
        "participacao": "2,8%",
        "participacaoCor": "emerald",
        "descricao": "Planta industrial da Ceratti (Ebert Indústria de Produtos Alimentícios) em Vinhedo/SP, com <strong class=\"text-emerald-400\">13.851 m² de ABL</strong> e 8m de pé direito. A Ceratti é uma marca tradicional de embutidos e frios premium no mercado brasileiro. Contrato de longo prazo com vencimento em Dez/2032. Relatório de Acompanhamento Imobiliário divulgado em Dez/2025.",
        "risco": "Baixo",
        "qualidade": "Boa",
        "relevancia": "Indústria alimentícia premium",
        "contrato": {
          "tipo": "Atípico",
          "termino": "Dez/2032",
          "terminoCor": "emerald",
          "reajuste": "IPCA",
          "multa": "Saldo remanescente do aluguel"
        },
        "pontos": [
          {
            "texto": "Contrato longo até Dez/2032 — 7 anos de receita previsível",
            "cor": "emerald"
          },
          {
            "texto": "Ceratti: marca premium consolidada no mercado de frios e embutidos",
            "cor": "emerald"
          },
          {
            "texto": "Setor de alimentos — demanda resiliente e anticíclica",
            "cor": "emerald"
          },
          {
            "texto": "Imóvel adaptado para uso específico (cold storage) — difícil reposicionamento",
            "cor": "amber"
          }
        ]
      },
      {
        "nome": "Rizobacter — Londrina/PR",
        "tipo": "Imóvel Híbrido — Agronegócio",
        "icone": "🌱",
        "corIcone": "emerald",
        "corBorda": "emerald",
        "participacao": "2,5%",
        "participacaoCor": "emerald",
        "descricao": "Planta industrial-logística da Rizobacter (multinacional argentina de inoculantes e biotecnologia agrícola) em Londrina/PR, com <strong class=\"text-emerald-400\">11.118 m² de ABL</strong>, 12m de pé direito e capacidade de piso de 6 ton/m². Contrato de muito longo prazo com vencimento em Mai/2043. O fundo possui CRI Rizobacter no valor de R$ 34,0 Mi (IPCA+8,0% a.a.).",
        "risco": "Muito Baixo",
        "qualidade": "Excelente",
        "relevancia": "Contrato mais longo do portfólio",
        "contrato": {
          "tipo": "Atípico BTS",
          "termino": "Mai/2043",
          "terminoCor": "emerald",
          "reajuste": "IPCA",
          "multa": "Saldo remanescente do aluguel"
        },
        "pontos": [
          {
            "texto": "Contrato até Mai/2043 — 17+ anos, o mais longo do portfólio",
            "cor": "emerald"
          },
          {
            "texto": "CRI Rizobacter de R$ 34 Mi (IPCA+8%) — receita adicional vinculada",
            "cor": "emerald"
          },
          {
            "texto": "Agronegócio: setor estratégico no Brasil, demanda resiliente",
            "cor": "emerald"
          },
          {
            "texto": "Multinacional argentina — risco país do controlador (mas operação 100% Brasil)",
            "cor": "amber"
          }
        ]
      },
      {
        "nome": "CD SantaCruz — Anápolis/GO (em expansão)",
        "tipo": "Galpão Logístico — Cosméticos/Farmacêutico",
        "icone": "💊",
        "corIcone": "emerald",
        "corBorda": "emerald",
        "participacao": "1,7%",
        "participacaoCor": "emerald",
        "descricao": "Centro de Distribuição da SantaCruz Distribuição em Anápolis/GO, com <strong class=\"text-emerald-400\">39.482 m² de ABL atual</strong>, 12m de pé direito e capacidade de piso de 6 ton/m². Em expansão (Fase 02) com ABL adicional de 23.348 m², elevando a ABL total para ~62.830 m². Obra 76% concluída em Dez/2025 (fundações, estruturas e cobertura finalizadas; pisos e acabamento em andamento). Contrato de longo prazo com vencimento em Nov/2035.",
        "risco": "Baixo",
        "qualidade": "Excelente",
        "relevancia": "Maior ativo em ABL direta (pós-expansão)",
        "contrato": {
          "tipo": "Atípico BTS",
          "termino": "Nov/2035",
          "terminoCor": "emerald",
          "reajuste": "IPCA",
          "multa": "Saldo remanescente do aluguel"
        },
        "pontos": [
          {
            "texto": "Contrato até Nov/2035 — 10 anos de receita previsível",
            "cor": "emerald"
          },
          {
            "texto": "Expansão Fase 02 (+23.348 m²) — 76% concluída, aumento de receita em breve",
            "cor": "emerald"
          },
          {
            "texto": "ABL pós-expansão de ~62.830 m² — um dos maiores galpões do portfólio",
            "cor": "blue"
          },
          {
            "texto": "Anápolis/GO: hub logístico estratégico do Centro-Oeste",
            "cor": "blue"
          },
          {
            "texto": "Risco de execução na obra (24% pendente) — prazo e custo a monitorar",
            "cor": "amber"
          }
        ]
      },
      {
        "nome": "CD Seropédica — Seropédica/RJ (Granado, EPL, Embelleze)",
        "tipo": "Condomínio Logístico — Multi-inquilino",
        "icone": "🏗️",
        "corIcone": "purple",
        "corBorda": "purple",
        "participacao": "2,7%",
        "participacaoCor": "purple",
        "descricao": "Condomínio logístico localizado no km 204 da Rodovia Presidente Dutra em Seropédica/RJ. ABL atual de <strong class=\"text-purple-400\">39.752 m²</strong> em terreno de 710.026 m², atualmente locado à Granado (1,3%), EPL (0,8%) e Embelleze (0,6%). Adquirido em Out/2025 por R$ 68 milhões (via SPE) no contexto da 10ª emissão. O grande diferencial é o potencial de desenvolvimento: o projeto prevê a construção de mais 5 módulos de galpões, elevando a ABL total para ~185.000 m². Aluguel mensal atual de ~R$ 520 mil.",
        "risco": "Moderado",
        "qualidade": "Boa",
        "relevancia": "Maior potencial de desenvolvimento",
        "contrato": {
          "tipo": "Típico (multi-inquilino)",
          "reajuste": "IPCA",
          "multa": "Padrão Lei 8.245/91"
        },
        "pontos": [
          {
            "texto": "Potencial de expansão para 185.000 m² (4,6x a ABL atual) — upside significativo",
            "cor": "emerald"
          },
          {
            "texto": "Terreno de 710 mil m² — reserva de valor para desenvolvimento futuro",
            "cor": "emerald"
          },
          {
            "texto": "Localizado na Rod. Presidente Dutra (RJ-SP) — corredor logístico principal",
            "cor": "emerald"
          },
          {
            "texto": "Multi-inquilino: Granado, EPL e Embelleze — diversificação no ativo",
            "cor": "blue"
          },
          {
            "texto": "Contratos típicos — menor previsibilidade que atípicos",
            "cor": "amber"
          },
          {
            "texto": "Desenvolvimento futuro exige capex adicional — ainda não precificado",
            "cor": "amber"
          }
        ]
      },
      {
        "nome": "Green House — Indaiatuba/SP (Outdoor)",
        "tipo": "Galpão Logístico — Comércio/Importação",
        "icone": "📦",
        "corIcone": "emerald",
        "corBorda": "emerald",
        "participacao": "2,0%",
        "participacaoCor": "emerald",
        "descricao": "Conjunto de 5 blocos logísticos (B, C, D, E e G) no Condomínio Green House em Indaiatuba/SP, com <strong class=\"text-emerald-400\">20.108 m² de ABL</strong> e pé direito de 10 a 12,5m. Locado à Outdoor Importação e Exportação. Adquirido em Set/2025 do FII Jive Properties III por R$ 43 milhões, com Cap Rate projetado de 11,35% no 1º ano. Aluguel mensal de ~R$ 407 mil. Garantia locatícia: caução de R$ 1,8 Mi.",
        "risco": "Moderado",
        "qualidade": "Boa",
        "relevancia": "Aquisição recente (Set/2025)",
        "contrato": {
          "tipo": "Típico (com aditivos)",
          "termino": "2026",
          "terminoCor": "red",
          "reajuste": "IPCA",
          "multa": "Padrão Lei 8.245/91"
        },
        "pontos": [
          {
            "texto": "Cap Rate de 11,35% a.a. — aquisição com bom rendimento implícito",
            "cor": "emerald"
          },
          {
            "texto": "Indaiatuba/SP próximo ao Aeroporto de Viracopos — localização logística premium",
            "cor": "emerald"
          },
          {
            "texto": "Contrato com vencimento em 2026 — necessidade de renovação iminente",
            "cor": "red"
          },
          {
            "texto": "Caução de R$ 1,8 Mi — garantia razoável mas não cobre vacância longa",
            "cor": "amber"
          },
          {
            "texto": "Pé direito variável (10-12,5m) — flexibilidade para diferentes ocupações",
            "cor": "blue"
          }
        ]
      },
      {
        "nome": "Hering — Anápolis/GO",
        "tipo": "Galpão Logístico — Têxtil/Varejo",
        "icone": "👕",
        "corIcone": "blue",
        "corBorda": "blue",
        "participacao": "2,2%",
        "participacaoCor": "blue",
        "descricao": "Centro de Distribuição da Cia. Hering (grupo Soma/Azzas 2154) em Anápolis/GO, com <strong class=\"text-blue-400\">31.853 m² de ABL</strong>, 12m de pé direito e capacidade de piso de 5 ton/m². A Hering é uma das marcas de moda mais reconhecidas do Brasil, agora parte do grupo Azzas 2154 (ex-Soma + Arezzo). Contrato com vencimento em Jan/2035.",
        "risco": "Baixo",
        "qualidade": "Boa",
        "relevancia": "Varejo premium de longo prazo",
        "contrato": {
          "tipo": "Atípico BTS",
          "termino": "Jan/2035",
          "terminoCor": "emerald",
          "reajuste": "IPCA",
          "multa": "Saldo remanescente do aluguel"
        },
        "pontos": [
          {
            "texto": "Contrato até Jan/2035 — 9 anos de receita garantida",
            "cor": "emerald"
          },
          {
            "texto": "Hering/Azzas 2154: grupo de moda consolidado com boa saúde financeira",
            "cor": "emerald"
          },
          {
            "texto": "Anápolis/GO: hub logístico do Centro-Oeste brasileiro",
            "cor": "blue"
          },
          {
            "texto": "Setor têxtil/moda — vulnerável a ciclos de consumo",
            "cor": "amber"
          }
        ]
      },
      {
        "nome": "Air Liquide — Campinas/SP",
        "tipo": "Imóvel Híbrido — Gases Industriais",
        "icone": "🔬",
        "corIcone": "emerald",
        "corBorda": "emerald",
        "participacao": "1,0%",
        "participacaoCor": "emerald",
        "descricao": "Imóvel localizado na Rua Ronald Cladstone Negri, 557, em Campinas/SP, com <strong class=\"text-emerald-400\">1.999 m² de ABL</strong> e 3,5m de pé direito, locado à Air Liquide Brasil. Aquisição concluída em Dez/2025, quando foi lavrada a escritura pública de compra e venda após o pagamento da última parcela (R$ 15,7 Mi). A Air Liquide é uma multinacional francesa líder mundial em gases industriais e medicinais (receita global de EUR 25+ bilhões), com rating investment grade.",
        "risco": "Muito Baixo",
        "qualidade": "Boa",
        "relevancia": "Multinacional francesa AAA",
        "contrato": {
          "tipo": "Atípico",
          "termino": "Dez/2027",
          "terminoCor": "amber",
          "reajuste": "IPCA",
          "multa": "Saldo remanescente do aluguel"
        },
        "pontos": [
          {
            "texto": "Air Liquide: multinacional francesa líder em gases — risco de crédito muito baixo",
            "cor": "emerald"
          },
          {
            "texto": "Aquisição concluída em Dez/2025 via BTLG11 — ativo em plena operação",
            "cor": "emerald"
          },
          {
            "texto": "ABL pequena (1.999 m²) — participação marginal na receita",
            "cor": "blue"
          },
          {
            "texto": "Vencimento em Dez/2027 — necessidade de monitorar renovação",
            "cor": "amber"
          }
        ]
      },
      {
        "nome": "Terreno Cabreúva — Cabreúva/SP",
        "tipo": "Terreno — Desenvolvimento Logístico",
        "icone": "🗺️",
        "corIcone": "amber",
        "corBorda": "amber",
        "participacao": "1,7%",
        "participacaoCor": "amber",
        "descricao": "Terreno de <strong class=\"text-amber-400\">429.726 m²</strong> em Cabreúva/SP, destinado ao desenvolvimento de um projeto logístico. Adquirido do BLMG11 em Set/2025 como parte da transação de R$ 125 milhões (que incluiu as cotas do Triple A). Gera receita contratual de ~R$ 350 mil/mês via contraprestação do BLMG11 (24 parcelas mensais de R$ 350 mil). Potencial de desenvolvimento de galpões logísticos em localização estratégica entre São Paulo e o interior paulista.",
        "risco": "Elevado",
        "qualidade": "Razoável",
        "relevancia": "Reserva de desenvolvimento",
        "contrato": {
          "tipo": "Contraprestação BLMG11 (24 parcelas)",
          "termino": "Set/2027",
          "terminoCor": "amber",
          "reajuste": "Fixo",
          "multa": "Conforme contrato BLMG11"
        },
        "pontos": [
          {
            "texto": "Terreno de 430 mil m² — potencial de desenvolvimento logístico significativo",
            "cor": "emerald"
          },
          {
            "texto": "Receita garantida de R$ 350 mil/mês (24 parcelas do BLMG11)",
            "cor": "emerald"
          },
          {
            "texto": "Ativo sem geração de renda própria — dependente de desenvolvimento futuro",
            "cor": "amber"
          },
          {
            "texto": "Necessidade de investimento (capex) para construção de galpões",
            "cor": "amber"
          },
          {
            "texto": "Localização entre SP e interior — potencial logístico no eixo Anhanguera/Bandeirantes",
            "cor": "blue"
          }
        ]
      },
      {
        "nome": "Demais ativos (Todimo, Camargo, Cepalgo, Copobras, Aptiv, Magna, etc.)",
        "tipo": "Portfólio diversificado — Logístico, Industrial e Híbrido",
        "icone": "🏢",
        "corIcone": "blue",
        "corBorda": "blue",
        "participacao": "24,5%",
        "participacaoCor": "blue",
        "descricao": "Conjunto de 15+ ativos menores que compõem a cauda longa do portfólio, incluindo: <strong class=\"text-blue-400\">Todimo</strong> (Cuiabá/MT, 23.857 m², venc. Dez/2027, 2,3%), <strong class=\"text-blue-400\">Camargo</strong> (Tietê/SP, 14.428 m², venc. Jan/2032, 2,3%), <strong class=\"text-blue-400\">Cepalgo</strong> (Aparecida de Goiânia/GO, 10.998 m², venc. Fev/2028, 1,4%), <strong class=\"text-blue-400\">Copobras</strong> (João Pessoa/PB, 22.360 m², venc. Abr/2028, 2,3%), <strong class=\"text-blue-400\">Aptiv</strong> (Espirito Santo do Pinhal/SP, 19.192 m², venc. Mar/2029, 1,9%), <strong class=\"text-blue-400\">Magna</strong> (Vinhedo/SP, 10.439 m², venc. Mai/2030, 1,6%), <strong class=\"text-blue-400\">Supermarket</strong> (RJ, 17.244 m², venc. Out/2028, 1,2%), <strong class=\"text-blue-400\">Martin Brower</strong> (Curitiba/PR, 6.592 m², venc. 2028, 1,7%), <strong class=\"text-blue-400\">CD Extrema</strong> (Extrema/MG, 11.616 m², venc. 2028), <strong class=\"text-blue-400\">CD Queimados</strong> (Queimados/RJ, 11.161 m², vago — 0,21% vacância), <strong class=\"text-blue-400\">CD Contagem</strong> (Contagem/MG, 12.722 m², venc. 2028), <strong class=\"text-blue-400\">Moinho Iguaçu</strong> (SMI/PR + Cascavel/PR, 15.102 m², venc. Jun/2027), <strong class=\"text-blue-400\">Eagleburgmann</strong> (Valinhos/SP, 3.489 m², venc. Ago/2037), <strong class=\"text-blue-400\">Mills</strong> (Camaçari/BA, 4.415 m², venc. Jun/2030), entre outros menores.",
        "risco": "Moderado",
        "qualidade": "Boa",
        "relevancia": "Diversificação do portfólio",
        "contrato": {
          "tipo": "Atípico e Típico (misto)",
          "termino": "2027 a 2037",
          "terminoCor": "blue",
          "reajuste": "IPCA (majoritário) / IGP-M / INPC",
          "multa": "Variável por contrato"
        },
        "pontos": [
          {
            "texto": "Alta diversificação: 15+ ativos em 10+ estados — mitiga risco de concentração",
            "cor": "emerald"
          },
          {
            "texto": "Nenhum ativo individual acima de 2,5% da receita — cauda longa equilibrada",
            "cor": "emerald"
          },
          {
            "texto": "Eagleburgmann com vencimento em 2037 — contrato de longuíssimo prazo",
            "cor": "emerald"
          },
          {
            "texto": "CD Queimados vago — única vacância do portfólio (0,21% do total)",
            "cor": "amber"
          },
          {
            "texto": "Copobras e Cepalgo com vencimentos em 2028 — monitorar renovação",
            "cor": "amber"
          },
          {
            "texto": "Moinho Iguaçu (2 unidades) vence em Jun/2027 — risco de não renovação",
            "cor": "amber"
          },
          {
            "texto": "Setores diversificados: varejo, auto, químico, alimentos, metalurgia, tecnologia",
            "cor": "blue"
          }
        ]
      }
    ],
    "resumo": "O portfólio do GGRC11 é composto por <strong class=\"text-emerald-400\">36 ativos</strong> diversificados em <strong class=\"text-blue-400\">12 estados</strong>, com predominância de galpões logísticos (67%), seguidos por industriais (17%) e híbridos (16%). Os 5 maiores locatários (Renault, Ambev, Americanas, Triple A e Aethra) respondem por <strong class=\"text-amber-400\">~41% da receita</strong>, enquanto os demais 30 locatários pulverizam o restante. O reajuste predominante é pelo <strong class=\"text-blue-400\">IPCA (90,28%)</strong>. Destaque para os desinvestimentos estratégicos em 2025 (Covolan por R$ 94,9 Mi e CD Campinas por R$ 77 Mi com TIR de 16,94%) e novas aquisições (Renault, Seropédica, Green House, Triple A/Cabreúva). O WAULT de <strong class=\"text-amber-400\">4,94 anos</strong> exige monitoramento dos vencimentos em 2027, quando ~26% da receita estará exposta a renovações."
  },
  "valuation": {
    "pvp": {
      "valor": "0,88",
      "descricao": "Cota negociada com <span class=\"text-emerald-400\">12% de desconto</span> sobre o valor patrimonial",
      "detalhes": [
        {
          "label": "VP/Cota",
          "valor": "R$ 11,22"
        },
        {
          "label": "Preço",
          "valor": "R$ 9,90",
          "cor": "emerald"
        }
      ]
    },
    "spread": {
      "valor": "4,31%",
      "label": "Spread vs NTN-B 5Y",
      "cor": "emerald",
      "descricao": "Prêmio significativo sobre o título público com isenção de IR para PF",
      "detalhe": "DY GGRC11 (12,12%) vs NTN-B 5Y (7,81%)"
    },
    "recomendacoes": {
      "valor": 15,
      "label": "Recomendações",
      "cor": "blue",
      "descricao": "Menções em carteiras recomendadas de corretoras e analistas",
      "detalhe": "FII logístico com DY atrativo e desconto sobre VP"
    }
  },
  "conclusao": {
    "paragrafos": [
      "O <strong class=\"text-emerald-400\">GGRC11</strong> encerra 2025 com <strong class=\"text-emerald-400\">recordes históricos</strong> em todos os indicadores: patrimônio de R$ 2,4 bilhões (+74,1%), base de <strong class=\"text-white\">257 mil cotistas</strong> (+82,1%), 36 ativos imobiliários (+24,1%), ABL de 711 mil m2 (+22,6%) e R$ 179 milhões distribuídos em rendimentos (+58,4%). O fundo se posicionou entre os <strong class=\"text-emerald-400\">3 FIIs com maior crescimento</strong> do mercado em 2025.",
      "A estratégia de <strong class=\"text-purple-400\">reciclagem de ativos</strong> se comprovou eficiente: venda da Covolan por R$ 94,9 Mi e do CD Campinas por R$ 77 Mi com <strong class=\"text-emerald-400\">TIR de 16,94%</strong> e lucro estimado de R$ 21,5 Mi (~R$ 0,10/cota). A vacância caiu de 4,08% para <strong class=\"text-emerald-400\">0,21%</strong>. Renovação do contrato da Ambev Santa Luzia por +5 anos reforça a estabilidade operacional.",
      "Para 2026, o guidance base de <strong class=\"text-emerald-400\">R$ 0,10/cota/mês</strong> (DY ~12,12%) não contempla potenciais ganhos adicionais como renovações contratuais, locação do galpão vago (Queimados) nem valores depositados em juízo pela Covolan. O <strong class=\"text-blue-400\">P/VP de 0,88</strong> oferece margem de segurança expressiva, e o <strong class=\"text-emerald-400\">spread de 431 bps sobre a NTN-B</strong> torna o fundo atrativo para investidores de renda."
    ],
    "pontosFortes": [
      "DY de 12,12% com spread de 431 bps sobre NTN-B",
      "99,79% de ocupação física",
      "35 locatários diversificados em 36 imóveis",
      "P/VP de 0,88 (12% de desconto)",
      "Sem taxa de performance",
      "Guidance de R$ 0,10/cota/mês para 2026",
      "Reciclagem de ativos com TIR de 16,94%",
      "Crescimento recorde em 2025 (+74,1% PL)"
    ],
    "pontosDeAtencao": [
      "WAULT curto de 4,94 anos",
      "Vencimentos relevantes em 2027 (~26% da receita)",
      "CRIs de R$ 273,9 Mi (11,4% do PL) com taxas elevadas",
      "Covolan em recuperação judicial (4,5% da receita)",
      "Taxa de administração de 1,10% acima de alguns pares",
      "Contrato Renault (11,5%) vence em 2027"
    ],
    "conclusaoFinal": "O GGRC11 é uma opção atrativa para investidores que buscam <strong class=\"text-emerald-400\">renda mensal consistente</strong> com DY acima de 12% e desconto significativo sobre o VP. A diversificação com 35 locatários em 12 estados mitiga riscos de concentração. O principal monitoramento deve ser sobre os <strong class=\"text-amber-400\">vencimentos de contratos em 2027</strong> e a <strong class=\"text-amber-400\">evolução da alavancagem via CRIs</strong>. A gestão ativa da Zagros Capital tem demonstrado competência na reciclagem de ativos e crescimento sustentável."
  },
  "footer": {
    "dataAnalise": "24/02/2026",
    "totalDocumentos": 762,
    "disclaimer": "Este material tem caráter exclusivamente informativo e não constitui recomendação de investimento. Rentabilidade passada não é garantia de rentabilidade futura."
  }
}