{
  "dataSnapshot": "2026-04-26",
  "atualizadoEm": "2026-04-26T22:31:19Z",
  "selicAtual": 14.75,
  "selicProjetada12m": 11.0,
  "ipcaAcumulado12m": null,
  "ipcaProjetado12m": 3.9892,
  "diCurto": null,
  "diMedio": null,
  "diLongo": null,
  "fontes": {
    "selicAtual": "BCB SGS 432",
    "selicProjetada12m": "BCB Focus (mediana, fim do ano alvo)",
    "ipcaAcumulado12m": "BCB SGS 13522",
    "ipcaProjetado12m": "BCB Focus (mediana, fim do ano alvo)",
    "di": "input manual (Anbima/B3)"
  }
}